{
  "name": "Johanna Lopez",
  "age": 21,
  "address": {
    "street": "Sawoj Point",
    "city": "Vesudat",
    "state": "AK",
    "zip": "38835"
  },
  "contact": {
    "phone": "(616) 963-7188",
    "servicePhone": "800447972"
  },
  "birthday": "2002-07-19T00:58:42.053Z",
  "ip": "192.231.250.158",
  "foo": "bar",
  "profile": {
    "about": "Begdovvub wivvo wup sahmomkib jem wa wob ba ru uleojlas diftuj fufewiv jimfuv uki dovkiblak cibago li. Opjigpo laga pinjuk latjajhoh puvtuted wu watoswo gos izzus deco ked gani jos koj leateog oci. Lu bag vaziaku zuhsiw wejvuler if is zeg wujlo pa vonnicdaf bu dummigep tufuja wo. Su juejpen sagabu okanarham orfegah bodu muhi lim aha lipaga utitit hoez gokuh gov cudedvak zeshel banlughol darcoba. Nin bi dutla ufi feuba fabujlip jovalwik dunis kor dakitruf bew ze vo.",
    "bio": "Bipgel mipurov ocfakmek gosso tarive busup cilokva zud aghak paasdep bu iz ihbe no piltum jivap. Nug lidliw dub fuj bahogho nafaz reg boz vovu jemped mecujata va ga howiskes ulalum gawikra ki. Tapcebar cizmokis hiddida co cas lez izuged zemorik lolko in inacib var balet ro cirosu dupjaguc ja mabibaza."
  },
  "apiKey": "fa0d181873541097e17d5935bcf24d64b2f3cbcd1eb2349eca3365fc947141bd",
  "currency": {
    "code": "JMD",
    "name": "Jamaica Dollar"
  }
}