{
  "name": "Alberta Hanson",
  "age": 46,
  "address": {
    "street": "Rolvam Court",
    "city": "Tatuwboj",
    "state": "VA",
    "zip": "41651"
  },
  "contact": {
    "phone": "(479) 535-6080",
    "servicePhone": "800989369"
  },
  "birthday": "1990-04-28T22:40:38.604Z",
  "ip": "70.94.179.69",
  "foo": "bar",
  "profile": {
    "about": "Kavusruk wepod zimi hiba saluje ducibno lu cug kulu am hobpun nakvorap. Nurgot bu duzli dunipko ubake muadaiw sa zoz docimri jonwup iweohe jujeke umibik ow popezuzur. Hovo gok osimage noffefla luwpaltar punje vocwez erjecgo jaha vejadwuw kuvezjo ha. Lapo ruwrijjek honawvu sivnogpuc fi dirce zikiho lasavi foknet orva gubu hoz hurvadwu.",
    "bio": "Se kevesnoh giav umzuhpu nodetlik bazme fe pegut icjahdif vegen si cetmedpir. Urpe ekoiwabi kucfejub mosduba zakla tum bofac dergi zozrez bajpun voup bourofe gi rujso gigkeg. Avazedlir fuvgol echulri bigeh hoepe uri de hidbuk zi sep dizem dotuzof oforeiku benis."
  },
  "apiKey": "732e5580cbd1c0e6fdbabba44fa56471188901499a7f7520bef83692b332afbc",
  "currency": {
    "code": "BZD",
    "name": "Belize Dollar"
  }
}